pytest_xflaky/__init__.py
pytest_xflaky/add_decorator.py
pytest_xflaky/github_blame.py
pytest_xflaky/plugin.py
pytest_xflaky-1.0.3.dist-info/LICENSE
pytest_xflaky-1.0.3.dist-info/METADATA
pytest_xflaky-1.0.3.dist-info/WHEEL
pytest_xflaky-1.0.3.dist-info/entry_points.txt
pytest_xflaky-1.0.3.dist-info/top_level.txt
pytest_xflaky-1.0.3.dist-info/RECORD
