Metadata-Version: 2.1
Name: pytest-xflaky
Version: 1.0.3
Summary: A simple plugin to use with pytest
Author-email: Tesorio <caio@tesorio.com>
Maintainer-email: Tesorio <caio@tesorio.com>
License: 
Project-URL: Repository, https://github.com/Tesorio/pytest-xflaky
Classifier: Framework :: Pytest
Classifier: Development Status :: 4 - Beta
Classifier: Intended Audience :: Developers
Classifier: Topic :: Software Development :: Testing
Classifier: Operating System :: OS Independent
Classifier: Programming Language :: Python
Classifier: Programming Language :: Python :: 3.10
Classifier: Programming Language :: Python :: 3.11
Classifier: Programming Language :: Python :: 3.12
Classifier: Programming Language :: Python :: 3 :: Only
Classifier: Programming Language :: Python :: Implementation :: CPython
Classifier: License :: OSI Approved :: MIT License
Requires-Python: >=3.10
License-File: LICENSE
Requires-Dist: pytest-json-report
Requires-Dist: pytest >=8.2.1
Requires-Dist: requests
Requires-Dist: tree-sitter
Requires-Dist: tree-sitter-python
